diki_translate/__init__.py
diki_translate/diki.py
diki_translate-1.0.dist-info/LICENSE
diki_translate-1.0.dist-info/METADATA
diki_translate-1.0.dist-info/WHEEL
diki_translate-1.0.dist-info/top_level.txt
diki_translate-1.0.dist-info/RECORD
