Metadata-Version: 2.1
Name: diki-translate
Version: 1.0
Summary: A module for translating words using diki.pl dictionary.
Home-page: https://github.com/mepavv/diki_translate
Author: Michał Pawłowski
Author-email: <michal.paw000@gmail.com>
License: MIT
Keywords: translation,scraper,api,polish
Classifier: License :: OSI Approved :: MIT License
License-File: LICENSE
Requires-Dist: requests
Requires-Dist: beautifulsoup4
